pydom/__init__.py
pydom/component.py
pydom/element.py
pydom/errors.py
pydom/page.py
pydom/py.typed
pydom/unicode_chars.py
pydom/version.py
pydom/context/__init__.py
pydom/context/context.py
pydom/context/standard/__init__.py
pydom/context/standard/transformers/__init__.py
pydom/context/standard/transformers/class_transformer.py
pydom/context/standard/transformers/dash_transformer.py
pydom/context/standard/transformers/falsy_transformer.py
pydom/context/standard/transformers/html_events_transformer.py
pydom/context/standard/transformers/inner_html_transformer.py
pydom/context/standard/transformers/simple_transformers.py
pydom/context/standard/transformers/style_transformer.py
pydom/html/__init__.py
pydom/html/a.py
pydom/html/abbr.py
pydom/html/address.py
pydom/html/area.py
pydom/html/article.py
pydom/html/aside.py
pydom/html/audio.py
pydom/html/b.py
pydom/html/base.py
pydom/html/bdi.py
pydom/html/bdo.py
pydom/html/blockquote.py
pydom/html/body.py
pydom/html/br.py
pydom/html/button.py
pydom/html/canvas.py
pydom/html/caption.py
pydom/html/cite.py
pydom/html/code.py
pydom/html/col.py
pydom/html/colgroup.py
pydom/html/data.py
pydom/html/datalist.py
pydom/html/dd.py
pydom/html/del_.py
pydom/html/details.py
pydom/html/dfn.py
pydom/html/dialog.py
pydom/html/div.py
pydom/html/dl.py
pydom/html/dt.py
pydom/html/em.py
pydom/html/embed.py
pydom/html/fieldset.py
pydom/html/figcaption.py
pydom/html/figure.py
pydom/html/footer.py
pydom/html/form.py
pydom/html/fragment.py
pydom/html/h1.py
pydom/html/h2.py
pydom/html/h3.py
pydom/html/h4.py
pydom/html/h5.py
pydom/html/h6.py
pydom/html/head.py
pydom/html/header.py
pydom/html/hgroup.py
pydom/html/hr.py
pydom/html/html.py
pydom/html/i.py
pydom/html/iframe.py
pydom/html/img.py
pydom/html/input.py
pydom/html/ins.py
pydom/html/kbd.py
pydom/html/label.py
pydom/html/legend.py
pydom/html/li.py
pydom/html/link.py
pydom/html/main.py
pydom/html/map.py
pydom/html/mark.py
pydom/html/menu.py
pydom/html/meta.py
pydom/html/meter.py
pydom/html/nav.py
pydom-0.4.2.dist-info/METADATA
pydom-0.4.2.dist-info/WHEEL
pydom-0.4.2.dist-info/entry_points.txt
pydom-0.4.2.dist-info/top_level.txt
pydom-0.4.2.dist-info/RECORD
