Metadata-Version: 2.4
Name: pydom
Version: 0.4.2
Summary: A Python package for creating and manipulating reusable HTML components
Author-email: Xpo Development <dev@xpo.dev>
Project-URL: Homepage, https://pydom.dev
Project-URL: Issues, https://github.com/xpodev/pydom/issues
Classifier: Development Status :: 4 - Beta
Classifier: Environment :: Web Environment
Classifier: Intended Audience :: Developers
Classifier: License :: OSI Approved :: MIT License
Classifier: Operating System :: OS Independent
Classifier: Programming Language :: Python :: 3
Classifier: Programming Language :: Python :: 3.8
Classifier: Programming Language :: Python :: 3.9
Classifier: Programming Language :: Python :: 3.10
Classifier: Programming Language :: Python :: 3.11
Classifier: Programming Language :: Python :: 3.12
Classifier: Programming Language :: Python :: 3.13
Requires-Python: >=3.8
Requires-Dist: cssutils==2.9.0
Requires-Dist: typing-extensions
